wingstructure/__init__.py
wingstructure/version.py
wingstructure/aero/__init__.py
wingstructure/aero/liftingline.py
wingstructure/aero/multhop.py
wingstructure/aero/nnliftingline.py
wingstructure/aero/polarinterp.py
wingstructure/data/__init__.py
wingstructure/data/wing.py
wingstructure/structure/__init__.py
wingstructure/structure/beammechanics.py
wingstructure/structure/mass.py
wingstructure/structure/material.py
wingstructure/structure/polygon.py
wingstructure/structure/section.py
wingstructure/structure/section_helper.py
wingstructure/structure/stickmodel.py
wingstructure-0.0.6.dist-info/LICENSE
wingstructure-0.0.6.dist-info/METADATA
wingstructure-0.0.6.dist-info/WHEEL
wingstructure-0.0.6.dist-info/top_level.txt
wingstructure-0.0.6.dist-info/RECORD
