Metadata-Version: 2.1
Name: wingstructure
Version: 0.0.6
Summary: A library for structure calculations in airplane wings
Home-page: https://github.com/akafliegdarmstadt/wingstructure
Author: helo
Author-email: kontakt@akaflieg.tu-darmstadt.de
License: MIT
Platform: UNKNOWN
Classifier: Programming Language :: Python :: 3
Classifier: License :: OSI Approved :: MIT License
Classifier: Natural Language :: English
Classifier: Topic :: Scientific/Engineering
Requires-Dist: numpy
Requires-Dist: scipy
Requires-Dist: pandas
Requires-Dist: sortedcontainers
Requires-Dist: matplotlib
Requires-Dist: pytest
Requires-Dist: strictyaml
Requires-Dist: Shapely
Requires-Dist: ipython
